README.rst
setup.py
lista_xml/__init__.py
lista_xml/titulos_cds.py
lista_xml.egg-info/PKG-INFO
lista_xml.egg-info/SOURCES.txt
lista_xml.egg-info/dependency_links.txt
lista_xml.egg-info/not-zip-safe
lista_xml.egg-info/requires.txt
lista_xml.egg-info/top_level.txt