Metadata-Version: 1.1
Name: lista-xml
Version: 0.0.1
Summary: Busca o Avatar com a Imagem do Usuario
Home-page: https://github.com/joaopauloramos/pypratico
Author: joaopauloramos
Author-email: joaozimvip@gamil.com
License: AGPL
Platform: UNKNOWN
Classifier: Development Status :: 4 - Beta
Classifier: Environment :: Web Environment
Classifier: Intended Audience :: Developers
Classifier: License :: OSI Approved :: GNU Affero General Public License v3 or later (AGPLv3+)
Classifier: Operating System :: OS Independent
Classifier: Programming Language :: Python :: 3.6
Classifier: Framework :: Paste
